bot_exts/__init__.py
bot_exts/cogs/__init__.py
bot_exts/cogs/base.py
bot_exts/cogs/orm.py
bot_exts/converters.py
bot_exts-0.1.5.dist-info/LICENSE
bot_exts-0.1.5.dist-info/WHEEL
bot_exts-0.1.5.dist-info/METADATA
bot_exts-0.1.5.dist-info/RECORD
