Metadata-Version: 2.1
Name: bot-exts
Version: 0.1.5
Summary: 
Author: TrixiS
Author-email: oficialmorozov@gmail.com
Requires-Python: >=3.8,<4.0
Classifier: Programming Language :: Python :: 3
Classifier: Programming Language :: Python :: 3.10
Classifier: Programming Language :: Python :: 3.8
Classifier: Programming Language :: Python :: 3.9
Provides-Extra: orm
Requires-Dist: nextcord (>=2.0.0-alpha.3,<3.0.0)
Requires-Dist: pydantic (>=1.8.2,<2.0.0)
Requires-Dist: tortoise-orm (>=0.17.8,<0.18.0); extra == "orm"
